{"menus":[{"section":"Modules","items":[{"title":"Product Videos","icon":"<i class=\"la la-video-camera\"><\/i>","url":"\/product-videos\/product-videos"},{"title":"Story Images","icon":"<i class=\"la la-list-ol\"><\/i>","url":"\/story\/story"},{"title":"Schedule","icon":"<i class=\"la la-check-circle\"><\/i>","url":"\/schedule\/schedule"},{"title":"Firing Process Slider","icon":"<i class=\"la la-image\"><\/i>","url":"\/firingprocessslider\/firing-process-slider"},{"title":"Coupon","icon":"<i class=\"la la-question-circle\"><\/i>","url":"\/coupon\/coupon"},{"title":"Firing Process Video","icon":"<i class=\"la la-video-camera\"><\/i>","url":"\/firingprocessvideo\/firing-process-video"},{"title":"Shipping Zone","icon":"<i class='la la-asterisk'><\/i>","url":"\/shippings\/shippings"},{"title":"Discount","icon":"<i class='la la-bitcoin'><\/i>","url":"\/discount\/discount"}]}]}